[
    {
        "type": "header",
        "header": "Мария Сибилла Мериан"
    },
    {
        "type": "epigraph",
        "content":
        {
            "quote": "И не подвластен сомненью твой твердый ответ изначальный.",
            "source": "С. Хермлин"
        }
    },
    {
        "type": "marginalis",
        "link": "merian.jpg",
        "source": "Мария Сибилла Мериан"
    },
    {
        "header": "Биографическая справка",
        "type": "article",
        "content": "<strong>Мериан, Мария Сибилла</strong> (1647&ndash;1717), выдающаяся немецкая художница, гравер, натуралист. В 1699&ndash;1701 гг. посетила Суринам, где чрезвычайно плодотворно изучала мир насекомых Южной Америки. Ей принадлежит книга «Метаморфозы суринамских насекомых». Значительная часть ее работ была приобретена Петром I и находится в России."
    },
    {
        "header": "Цитаты",
        "type": "quote",
        "content":
        [
            {
                "quote": "Виднейший в эпоху барокко мастер гравюры и рисунков цветов, плодов и мелких животных. Работала также в области живописи. После учебы у отчима, мастера цветочных натюрмортов Якоба Мареля, и Абрахама Миньона поселилась вместе со своим супругом сначала в Нюрнберге, затем в Амстердаме.",
                "source": "Энциклопедия искусства., М., &laquo;АСТ&raquo;, 1999, стр. 444."
            },
            {
                "quote": "Госпожу Мериан призвала в Суринам поистине героическая любовь к насекомым; это было целое событие — женщина пересекла моря, чтобы рисовать американских насекомых, после того, как она изобразила большое число европейских: вернулась она оттуда с таблицами, запечатлевшими внушительное количество великолепных видов бабочек и гусениц, которые были превосходно гравированы.",
                "source": "Р. Реомюр о Марии Сибилле Мериан. /&nbsp;Цит. по: Копанева Н. П. Живые краски Мериан. // Наука из первых рук., №. 1, (31), 2010., стр. 98."
            }
        ]
    },
    {
        "header": "Литература",
        "type": "list",
        "content":
        [
            {"title": "Европейское искусство. Энциклопедия. Живопись. Скульптура. Графика. В 3 томах", "publishing": "М., &laquo;Белый город&raquo;", "year": "2006"},
            {"author": "Копанева Н. П.", "title": "Живые краски Мериан", "publishing": "// Наука из первых рук", "year": "2010&nbsp;№&nbsp;1&nbsp;(31)"},
            {"author": "Лукина Т. А.", "title": "Мария Сибилла Мериан, 1647-1717", "publishing": "Л., &laquo;Наука&raquo;", "year": "1980"},
            {"title": "Петр I и Голландия. Русско-голландские научные и художественные связи в эпоху Петра Великого. Антология", "publishing": "СПб., &laquo;Европейский дом&raquo;", "year": "1998"},
            {"title": "Энциклопедия искусства", "publishing": "М., &laquo;АСТ&raquo;", "year": "1999"}
        ]
    }
]
