[
    {
        "type": "epigraph",
        "content":
        {
            "quote": "У красот природы  собственников нет, оттого и нет  никаких препятствий усладе сердца моего",
            "source": "Камо&ndash;Но Тёмей. Записки из кельи"
        }
    },
    {
        "type": "image",
        "link": "Akadzome.jpg",
        "source": "Моромаса. Сцена в интерьере. XVIII в. Фрагмент."
    },
    {
        "header": "Биографическая справка",
        "type": "article",
        "content": "<strong>Акадзомэ Эмон</strong> (вторая половина X века &ndash; после 1041 г.). Собственно годы рождения и смерти Акадзомэ Эмон точно не известны, известно только, что в 1041 году ей было уже более 80 лет. Она принадлежит к так называемым &laquo;тридцати шести бессмертным поэтам&raquo; Средневековья. Была благородного происхождения. В юности состояла сперва в свите супруги канцлера <strong>Фудзивара Митинага</strong> (966&ndash; 1027), а позднее &mdash; в свите его дочери, императрицы <strong>Сёси</strong>. Известно также, что Акадзомэ Эмон была замужем за <strong>Оэ Масахира</strong> (наместник провинции Овари). У них было двое сыновей. Литературное наследие поэтессы состоит из ее домашней антологии &laquo;Акадзомэ Эмонсю&raquo;, которая включает в себя свыше 600 пятистиший. Ее произведения присутствуют во многих классических антологиях. Кроме того её считают автором исторического романа &laquo;Повесть о расцвете&raquo; (&laquo;Эйга&ndash;мо&ndash;ногатари&raquo;), написанного в XI в."
    },
    {
        "header": "Цитаты",
        "type": "rhyme",
        "content":
        [
            {
                "header": "***",
                "quote": "В старину за цветы<br>Люди снег принимали. <br>Но этой весной &mdash;<br>Наоборот всё &mdash; цветы <br>Кажутся хлопьями снега.<br>",
                "source": "перевод Т. Соколовой&ndash;Делюсиной"
            },
            {
                "header": "***",
                "quote": "Эти цветы<br>Хотела увидеть на ветках,<br>В полной красе,<br>Но увы, возвращаюсь ни с чем,<br>По глубокому снегу ступая...",
                "source": "перевод Т. Соколовой&ndash;Делюсиной"
            },
            {
                "header": "***",
                "quote": "На цветущие вишни<br>Я и взглянуть не успела &mdash; <br>Осыпались разом. <br>Налюбуюсь же в утешенье <br>Хотя бы весенней луной.",
                "source": "перевод Т. Соколовой&ndash;Делюсиной"
            },
            {
                "header": "***",
                "quote": "Летний ливень<br>Отшумел, и вот уже в небе<br>Сияет луна.<br>Только дождь моих слез<br>Льет и льет бесконечно.",
                "source": "перевод Т. Соколовой&ndash;Делюсиной"
            },
            {
                "header": "***",
                "quote": "Проснувшись едва,<br>Выгляну в сад &mdash;  хризантемы<br>В каплях росы.<br>Лунный свет золотыми волнами<br>Набегает, зыбко струится.",
                "source": "перевод Т. Соколовой&ndash;Делюсиной"
            }
        ]
    },
    {
        "header": "Литература",
        "type": "list",
        "content":
        [
            {"title": "Японская поэзия", "publishing": "СПб, &laquo;Северо-Запад&raquo;", "year": "2000"},
            {"title": "Тысяча журавлей. Антология японской классической поэзии", "publishing": "СПб, &laquo;Азбука-классика&laquo;", "year": "2004"}
        ]
    }
]
