[
    {
        "type": "header",
        "header": "Лени Рифеншталь"
    },
    {
        "type": "epigraph",
        "content":
        {
            "quote": "Вдруг я&nbsp;увидела, как медленно из тумана проступают старые руины сооружений классической Олимпии, а&nbsp;перед глазами проплывают греческие храмы и&nbsp;скульптуры. Ахилл и&nbsp;Афродита, Медуза и&nbsp;Зевс&#133;",
            "source": "Лени Рифеншталь о&nbsp;фильме <dfn>&laquo;Олимпия&raquo;</dfn>"
        }
    },
    {
        "type": "image",
        "link": "leni.jpg",
        "source": "Лени Рифеншталь"
    },
    {
        "header": "Биографическая справка",
        "type": "article",
        "content": "<strong>Лени Рифеншталь</strong> (1902&ndash;2003&nbsp;гг.) в&nbsp;Берлине в&nbsp;семье коммерсанта. Еще будучи девочкой отличалась железной волей, честолюбием и&nbsp;многогранностью интересов. С&nbsp;четырех лет она интересовалась театром и&nbsp;танцами. С&nbsp;19&nbsp;лет занималась балетом, проявила незаурядные способности. Выступала во многих европейских странах. Позднее снималась в&nbsp;кино. С&nbsp;1931&nbsp;г. снимает собственные фильмы. В&nbsp;фильме &laquo;Голубой свет&nbsp;&mdash; легенда Доломитовых Альп&raquo; она выступает в&nbsp;роли деревенской девушки <strong>Ютты</strong> и&nbsp;как режиссер. Уже эта первая проба ее режиссерских способностей была в&nbsp;1932&nbsp;году отмечена серебряной медалью на биеннале в&nbsp;Венеции. Вскоре Рифеншталь познакомилась с <strong>Гитлером</strong> и&nbsp;стала снимать фильмы по его заказу (&laquo;<cite>Победа веры</cite>&raquo;, &laquo;<cite>Триумф воли</cite>&raquo;). Затем Лени Рифеншталь сняла фильм &laquo;<cite>Олимпия</cite>&raquo;, посвященный Олимпийским играм 1936&nbsp;года в&nbsp;Берлине. Она создала произведение искусства. В&nbsp;1939&nbsp;году Олимпийский комитет присудил режиссеру золотую медаль. После краха Третьего рейха Рифеншталь арестовали. Ее обвиняли в&nbsp;пропаганде в&nbsp;пользу Гитлера и&nbsp;НСДАП. Была оправдана. Продолжала снимать фильмы. Работала до последних дней своей жизни, увлекалась подводным плаваньем. Умерла в&nbsp;2003&nbsp;г."
    },
    {
        "header": "Хронология",
        "type": "table",
        "content":
        [
            {
                "column1": "22.08.1902&nbsp;г.",
                "column2": "родилась Лени Рифеншталь."
            },
            {
                "column1": "1921&nbsp;г.",
                "column2": "Лени начинает учиться классическому балету."
            },
            {
                "column1": "1925&nbsp;г.",
                "column2": "Рифеншталь принимает решение стать киноактрисой."
            },
            {
                "column1": "1925&ndash;1931&nbsp;гг.",
                "column2": "сьемки в&nbsp;различных фильмах."
            },
            {
                "column1": "1931&nbsp;г.",
                "column2": "Рифеншталь основала компанию по производству фильмов."
            },
            {
                "column1": "1932&nbsp;г.",
                "column2": "фильм &laquo;<dfn>Голубой свет&nbsp;&mdash; легенда Доломитовых Альп</dfn>&raquo; отмечен серебряной медалью в&nbsp;Венеции."
            },
            {
                "column1": "1932&nbsp;г.",
                "column2": "знакомство с&nbsp;А.&nbsp;Гитлером."
            },
            {
                "column1": "1933&nbsp;г.",
                "column2": "Рифеншталь снимает по заказу НСДАП фильм <dfn>&laquo;Победа веры&raquo;</dfn> о&nbsp;<nobr>5-м</nobr> имперском съезде партии."
            },
            {
                "column1": "1936&ndash;1939&nbsp;гг.",
                "column2": "съемки фильма <dfn>&laquo;Олимпия&raquo;</dfn>"
            },
            {
                "column1": "1939&nbsp;г.",
                "column2": "Олимпийский комитет присудил режиссеру за фильм <dfn>&laquo;Олимпия&raquo;</dfn> золотую медаль."
            },
            {
                "column1": "21.03.1944&nbsp;г.",
                "column2": "брак с&nbsp;<strong>Петером Якобом</strong>, капитаном горнострелковых частей."
            },
            {
                "column1": "1948&nbsp;г.",
                "column2": "Рифеншталь привлечена к&nbsp;суду, по обвинению в&nbsp;пропаганде нацистской идеологии. Оправдана."
            },
            {
                "column1": "1950&ndash;1975&nbsp;гг.",
                "column2": "Рифеншталь снимает фильмы и&nbsp;занимается фотографией."
            },
            {
                "column1": "1975&nbsp;г.",
                "column2": "серия фотографий Рифеншталь о&nbsp;малоизвестном племени <dfn>нуба</dfn> в&nbsp;Судане признана лучшей фотографической работой 1975&nbsp;года."
            },
            {
                "column1": "1995&nbsp;г.",
                "column2": "ретроспективный показ творчества Лени Рифеншталь в&nbsp;Милане."
            },
            {
                "column1": "1997&nbsp;г.",
                "column2": "в&nbsp;Риме, в&nbsp;реставрированном дворце &laquo;Палаццо делле Экспозиционе&raquo; состоялся праздник, посвященный творчеству Лени Рифеншталь."
            },
            {
                "column1": "9.09.2003&nbsp;г.",
                "column2": "Лени Рифеншталь умерла."
            }
        ]
    },
    {
        "header": "Цитаты",
        "type": "quote",
        "content":
        [
            {
                "quote": "Ее талант стал ее трагедией&#133; Она была слепа, потому что была одержима, все время, подобно лазерному лучу, сосредоточивалась только на своей работе, не глядя ни налево, ни направо&#133; Но в&nbsp;такое время, как тогда, в&nbsp;Германии, человек обязан оглядываться по сторонам, а&nbsp;не быть простым лазерным лучом. От этого ничем не отговоришься, эту ответственность, этот груз ей придется нести всегда.",
                "source": "Рей Мюллер"
            },
            {
                "quote": "Кроме работы меня ничего не интересует.",
                "source": "Лени Рифеншталь"
            },
            {
                "quote": "&#133;появилась фигура дискобола Мирона. Я&nbsp;мечтала о&nbsp;том, как она превращается в&nbsp;человека из плоти и&nbsp;крови и&nbsp;под лупой времени начинает вращать диск&nbsp;&mdash; статуи превращались в&nbsp;храмовых танцовщиц, исчезающих в&nbsp;пламени, это олимпийский огонь, от которого зажигают факел и&nbsp;несут его от храма Зевса в&nbsp;современный Берлин 1936&nbsp;года&nbsp;&mdash; мост от античности в&nbsp;настоящее время.",
                "source": "Лени Рифеншталь о&nbsp;фильме &laquo;Олимпия&raquo;"
            },
            {
                "quote": "В&nbsp;ходе подготовки к&nbsp;съездам я&nbsp;неоднократно встречался с&nbsp;женщиной, которая произвела на меня впечатление, еще когда я&nbsp;был студентом: Лени Рифеншталь, звезда или режиссер в&nbsp;известных фильмах о&nbsp;горнолыжниках.",
                "source": "Альберт Шпеер"
            },
            {
                "quote": "Как единственная женщина с&nbsp;официальными функциями в&nbsp;партийном механизме, она часто противостояла всей партийной организации, которая поначалу готова была поднять против нее бунт. Политические руководители, традиционно враждебно относящиеся к&nbsp;женскому движению, словно вызов воспринимали уверенное поведение этой женщины, которая без тени смущения командовала мужчинами, преследуя свои цели.",
                "source": "Альберт Шпеер"
            }
        ]
    },
    {
        "header": "Литература",
        "type": "list",
        "content":
        [
            {"title": "Энциклопедия Третьего Рейха", "publishing": "М., &laquo;Миф&raquo;", "year": "1999"},
            {"author": "Семашко&nbsp;И.&nbsp;И.", "title": "100 великих женщин", "publishing": "М.", "year": "2000"},
            {"author": "Лени Рифеншталь", "title": "Мемуары", "publishing": "&laquo;Ладомир&raquo;", "year": "2006"},
            {"author": "Одри Салкелд", "title": "Лени Рифеншталь. Триумф и&nbsp;воля", "publishing": "М., &laquo;Эксмо&raquo;", "year": "2005"},
            {"author": "Шпеер&nbsp;А.", "title": "Воспоминания", "publishing": "Смоленск-Москва", "year": "1997"}
        ]
    }
]
